asws3-1.0.1.dist-info/DESCRIPTION.rst
asws3-1.0.1.dist-info/METADATA
asws3-1.0.1.dist-info/RECORD
asws3-1.0.1.dist-info/WHEEL
asws3-1.0.1.dist-info/metadata.json
asws3-1.0.1.dist-info/top_level.txt
websocket/__init__.py
websocket/client.py
websocket/enums.py
websocket/reasons.py
websocket/server.py
websocket/http/__init__.py
websocket/http/handshake.py
websocket/stream/__init__.py
websocket/stream/buffer.py
websocket/stream/fragment.py
websocket/stream/reader.py
websocket/stream/writer.py
