Metadata-Version: 2.0
Name: asws3
Version: 1.0.1
Summary: Asynchronous websockets in python 3.6
Home-page: https://github.com/regiontog/asws
Author: Erlend Tobiassen
Author-email: erlentob@stud.ntnu.no
License: UNKNOWN
Keywords: websocket,python3.6,asynchronous,asyncio,async
Platform: UNKNOWN
